ctdvis/__init__.py
ctdvis/config.py
ctdvis/datahandler.py
ctdvis/filter.py
ctdvis/session.py
ctdvis/utils.py
ctdvis/callbacks/__init__.py
ctdvis/callbacks/cbs.py
ctdvis/etc/settings.json
ctdvis/etc/vis_setup/deep_vis.json
ctdvis/etc/vis_setup/nos_vis.json
ctdvis/etc/vis_setup/oden_vis.json
ctdvis/etc/vis_setup/sgus_vis.json
ctdvis/etc/vis_setup/slua_vis.json
ctdvis/etc/vis_setup/smhi_expedition_vis.json
ctdvis/etc/vis_setup/smhi_vis.json
ctdvis/etc/vis_setup/umsc_vis.json
ctdvis/readers/__init__.py
ctdvis/readers/json_reader.py
ctdvis/readers/yml.py
ctdvis/sources/__init__.py
ctdvis/sources/data.py
ctdvis/sources/ts.py
ctdvis/tools/__init__.py
ctdvis/tools/quality_control.py
ctdvis/widgets/__init__.py
ctdvis/widgets/directory_selection.py
ctdvis/widgets/paragraph.py
ctdvis-0.1.10.dist-info/LICENSE
ctdvis-0.1.10.dist-info/METADATA
ctdvis-0.1.10.dist-info/WHEEL
ctdvis-0.1.10.dist-info/top_level.txt
ctdvis-0.1.10.dist-info/RECORD
